bedhost/__init__.py
bedhost/__main__.py
bedhost/_version.py
bedhost/cli.py
bedhost/const.py
bedhost/data_models.py
bedhost/exceptions.py
bedhost/helpers.py
bedhost/main.py
bedhost/routers/bed_api.py
bedhost/routers/bedset_api.py
bedhost/routers/search_api.py
bedhost/static/bedbase_bug.ico
bedhost/static/bedbase_bug.svg
bedhost/static/bedbase_logo.svg
bedhost/static/index.html
bedhost/static/postgres_icon.png
bedhost/static/query-builder-elasticsearch.js
bedhost/static/query-builder.standalone.min.js
bedhost/static/style.css
bedhost/templates/page.html
bedhost-0.2.0.dist-info/LICENSE.txt
bedhost-0.2.0.dist-info/METADATA
bedhost-0.2.0.dist-info/WHEEL
bedhost-0.2.0.dist-info/entry_points.txt
bedhost-0.2.0.dist-info/top_level.txt
bedhost-0.2.0.dist-info/RECORD
