Metadata-Version: 2.1
Name: bedhost
Version: 0.2.0
Summary: A database server application that provides both a RESTful API and GUI for access to BED files and related basic statistics
Home-page: 
Author: Oleksandr Khoroshevskyi, Michal Stolarczyk, Ognen Duzlevski, Bingjie Xue, Nathan Sheffield
License: BSD2
Keywords: project,bioinformatics,sequencing,ngs,workflow,GUI,bed,server
Classifier: Development Status :: 4 - Beta
Classifier: License :: OSI Approved :: BSD License
Classifier: Programming Language :: Python :: 3.8
Classifier: Programming Language :: Python :: 3.9
Classifier: Programming Language :: Python :: 3.10
Classifier: Programming Language :: Python :: 3.11
Classifier: Topic :: Scientific/Engineering :: Bio-Informatics
License-File: LICENSE.txt
Requires-Dist: bbconf >=0.4.0
Requires-Dist: fastapi >=0.103.0
Requires-Dist: geniml >=0.1.0
Requires-Dist: logmuse >=0.2.7
Requires-Dist: markdown
Requires-Dist: requests
Requires-Dist: setuptools
Requires-Dist: uvicorn
Requires-Dist: yacman >=0.9.2
